{
    "birth_date": "1936-12-14",
    "birth_place": "New York, New York, United States",
    "died": null,
    "fai_flight_count": 2,
    "fai_flight_list": [
        {
            "date": "1983-11-28",
            "duration": "10d 7h 47m 24s",
            "mission": "STS-9"
        },
        {
            "date": "1990-12-02",
            "duration": "8d 23h 5m 8s",
            "mission": "STS-35"
        }
    ],
    "first_name": "Robert Allan Ridley",
    "img": "https://www.worldspaceflight.com/bios/photos/unitedstates/parker-r.jpg",
    "last_name": "Parker\"Bob\"",
    "name": "Robert Allan  Ridley Parker\"Bob\"",
    "nationality": "American",
    "selection_date": "1967-08-04",
    "selection_group": "NASA Group 6",
    "status": "Retired"
}