{
    "birth_date": "1974-08-19",
    "birth_place": "Bugulma, Russia",
    "died": null,
    "fai_flight_count": 1,
    "fai_flight_list": [
        {
            "date": "2016-10-19",
            "duration": "173d 3h 14m 46s",
            "mission": "Soyuz MS-02"
        }
    ],
    "first_name": "Sergei Nikolaevich",
    "img": "https://www.worldspaceflight.com/bios/photos/russia/ryzhikov-s.jpg",
    "last_name": "Ryzhikov",
    "name": "Sergei Nikolaevich Ryzhikov",
    "nationality": "Russian",
    "selection_date": "2006-10-28",
    "selection_group": "Air Force Group 14",
    "status": "Active"
}