{
    "birth_date": "1935-07-03",
    "birth_place": "Santa Rita, New Mexico, United States",
    "died": null,
    "eva_count": 6,
    "eva_list": [
        {
            "date": "1972-12-11",
            "duration": "7h 12m",
            "mission": "Apollo 17"
        },
        {
            "date": "1972-12-12",
            "duration": "7h 37m",
            "mission": "Apollo 17"
        },
        {
            "date": "1972-12-13",
            "duration": "7h 15m",
            "mission": "Apollo 17"
        },
        {
            "date": "1972-12-14",
            "duration": "7m",
            "mission": "Apollo 17"
        },
        {
            "date": "1972-12-14",
            "duration": "4m",
            "mission": "Apollo 17"
        },
        {
            "date": "1972-12-17",
            "duration": "1h 6m",
            "mission": "Apollo 17"
        }
    ],
    "fai_flight_count": 1,
    "fai_flight_list": [
        {
            "date": "1972-12-07",
            "duration": "12d 13h 51m 59s",
            "mission": "Apollo 17"
        }
    ],
    "first_name": "Harrison Hagan",
    "img": "https://www.worldspaceflight.com/bios/photos/unitedstates/schmitt-h.jpg",
    "last_name": "Schmitt\"Jack\"",
    "name": "Harrison Hagan Schmitt\"Jack\"",
    "nationality": "American",
    "notes": "Schmitt was not an active participant in the 17 December 1972 EVA.",
    "selection_date": "1965-06-28",
    "selection_group": "NASA Group 4",
    "status": "Retired"
}