{
    "birth_date": "1969-12-24",
    "birth_place": "Nevinnomyssk , Stavropol , Russia",
    "died": null,
    "eva_count": 3,
    "eva_list": [
        {
            "date": "2010-11-15",
            "duration": "6h 28m",
            "mission": "ISS Expedition 25"
        },
        {
            "date": "2011-01-21",
            "duration": "5h 27m",
            "mission": "ISS Expedition 26"
        },
        {
            "date": "2011-02-16",
            "duration": "4h 51m",
            "mission": "ISS Expedition 26"
        }
    ],
    "fai_flight_count": 2,
    "fai_flight_list": [
        {
            "date": "2010-10-07",
            "duration": "159d 8h 43m 10s",
            "mission": "Soyuz TMA-01M"
        },
        {
            "date": "2016-03-18",
            "duration": "172d 3h 46m 22s",
            "mission": "Soyuz TMA-20M"
        }
    ],
    "first_name": "Oleg Ivanovich",
    "img": "https://www.worldspaceflight.com/bios/photos/russia/skripochka-o.jpg",
    "last_name": "Skripochka",
    "name": "Oleg Ivanovich  Skripochka",
    "nationality": "Russian",
    "selection_date": "1997-07-28",
    "selection_group": "Energia Engineer Group 14",
    "status": "Active"
}